pydbuilder/__init__.py
pydbuilder/language.json
pydbuilder/pydbuilder.py
pydbuilder/settings.json
pydbuilder-1.0.18.dist-info/METADATA
pydbuilder-1.0.18.dist-info/WHEEL
pydbuilder-1.0.18.dist-info/entry_points.txt
pydbuilder-1.0.18.dist-info/top_level.txt
pydbuilder-1.0.18.dist-info/RECORD
