Metadata-Version: 2.1
Name: pydbuilder
Version: 1.0.18
Summary: Utility for creating pyd files using Cython
Author: Cherepok3
Requires-Dist: setuptools
Requires-Dist: cython
